databend_driver/__init__.py
databend_driver/__init__.pyi
databend_driver/_databend_driver.cpython-38-x86_64-linux-gnu.so
databend_driver-0.33.4.dist-info/METADATA
databend_driver-0.33.4.dist-info/WHEEL
databend_driver-0.33.4.dist-info/RECORD
